{
  "paper_id": "A6",
  "source_file": "/org/caep-xuben/yangzijiang/yzj/datasets/Al_82/Al_82_papers/output/A6/preprocess/cleaned_input.md",
  "chunk_count": 8,
  "chunks": [
    {
      "chunk_id": "chunk_0001",
      "section": "Review Article",
      "section_index": 1,
      "paragraph_start": 1,
      "paragraph_end": 53,
      "char_start": 0,
      "char_end": 13077,
      "token_estimate": 3269
    },
    {
      "chunk_id": "chunk_0002",
      "section": "1.1.3. Phase diagram",
      "section_index": 9,
      "paragraph_start": 53,
      "paragraph_end": 112,
      "char_start": 11813,
      "char_end": 32960,
      "token_estimate": 5286
    },
    {
      "chunk_id": "chunk_0003",
      "section": "3.1.2. Grain refinement strengthening",
      "section_index": 18,
      "paragraph_start": 112,
      "paragraph_end": 146,
      "char_start": 32246,
      "char_end": 50193,
      "token_estimate": 4486
    },
    {
      "chunk_id": "chunk_0004",
      "section": "3.2.1. Single ferrite steel",
      "section_index": 24,
      "paragraph_start": 146,
      "paragraph_end": 227,
      "char_start": 50072,
      "char_end": 69420,
      "token_estimate": 4837
    },
    {
      "chunk_id": "chunk_0005",
      "section": "4. Application performance of FeeMneAleC low-density steels",
      "section_index": 28,
      "paragraph_start": 227,
      "paragraph_end": 314,
      "char_start": 69359,
      "char_end": 89157,
      "token_estimate": 4949
    },
    {
      "chunk_id": "chunk_0006",
      "section": "4.4. Hydrogen embrittlement",
      "section_index": 32,
      "paragraph_start": 314,
      "paragraph_end": 344,
      "char_start": 88898,
      "char_end": 96919,
      "token_estimate": 2005
    },
    {
      "chunk_id": "chunk_0007",
      "section": "Declaration of competing interest",
      "section_index": 37,
      "paragraph_start": 344,
      "paragraph_end": 352,
      "char_start": 96870,
      "char_end": 119563,
      "token_estimate": 5673
    },
    {
      "chunk_id": "chunk_0008",
      "section": "r e f e r e n c e s",
      "section_index": 38,
      "paragraph_start": 352,
      "paragraph_end": 356,
      "char_start": 116161,
      "char_end": 124130,
      "token_estimate": 1992
    }
  ]
}